AUTHORS.rst
CONTRIBUTING.rst
HISTORY.rst
LICENSE
MANIFEST.in
README.rst
setup.cfg
setup.py
docs/Makefile
docs/authors.rst
docs/conf.py
docs/contributing.rst
docs/history.rst
docs/index.rst
docs/installation.rst
docs/make.bat
docs/readme.rst
docs/usage.rst
gitdeploy/__init__.py
gitdeploy/cli.py
gitdeploy/gitdeploy.py
gitdeploy.egg-info/PKG-INFO
gitdeploy.egg-info/SOURCES.txt
gitdeploy.egg-info/dependency_links.txt
gitdeploy.egg-info/entry_points.txt
gitdeploy.egg-info/not-zip-safe
gitdeploy.egg-info/requires.txt
gitdeploy.egg-info/top_level.txt
tests/__init__.py
tests/test_gitdeploy.py