Metadata-Version: 1.1
Name: gitdeploy
Version: 0.1.0
Summary: A service that updates local directories based on changes to a remote git repository
Home-page: https://github.com/zdzielinski/gitdeploy
Author: Zachariah Dzielinski
Author-email: zachdzielinski@gmail.com
License: GNU General Public License v3
Keywords: gitdeploy
Platform: UNKNOWN
Classifier: Development Status :: 2 - Pre-Alpha
Classifier: Intended Audience :: Developers
Classifier: License :: OSI Approved :: GNU General Public License v3 (GPLv3)
Classifier: Natural Language :: English
Classifier: Programming Language :: Python :: 2
Classifier: Programming Language :: Python :: 2.6
Classifier: Programming Language :: Python :: 2.7
Classifier: Programming Language :: Python :: 3
Classifier: Programming Language :: Python :: 3.3
Classifier: Programming Language :: Python :: 3.4
Classifier: Programming Language :: Python :: 3.5
